{
  "id": "7761e232-6e92-4cb2-ae86-f6e8747f47ca",
  "prevId": "b7b5230b-1c75-4f0e-b77f-dcb486b76752",
  "version": "6",
  "dialect": "postgresql",
  "tables": {
    "public.users": {
      "name": "users",
      "schema": "",
      "columns": {
        "id": {
          "name": "id",
          "type": "uuid",
          "primaryKey": true,
          "notNull": true
        },
        "email": {
          "name": "email",
          "type": "text",
          "primaryKey": false,
          "notNull": true
        },
        "display_name": {
          "name": "display_name",
          "type": "text",
          "primaryKey": false,
          "notNull": false
        },
        "payday_day": {
          "name": "payday_day",
          "type": "integer",
          "primaryKey": false,
          "notNull": false
        },
        "payday_type": {
          "name": "payday_type",
          "type": "text",
          "primaryKey": false,
          "notNull": false
        },
        "expected_monthly_income": {
          "name": "expected_monthly_income",
          "type": "integer",
          "primaryKey": false,
          "notNull": false
        },
        "minimum_cash_buffer": {
          "name": "minimum_cash_buffer",
          "type": "integer",
          "primaryKey": false,
          "notNull": false,
          "default": 0
        },
        "planned_investing_protected": {
          "name": "planned_investing_protected",
          "type": "boolean",
          "primaryKey": false,
          "notNull": false,
          "default": true
        },
        "locale": {
          "name": "locale",
          "type": "text",
          "primaryKey": false,
          "notNull": false,
          "default": "'en'"
        },
        "currency": {
          "name": "currency",
          "type": "text",
          "primaryKey": false,
          "notNull": false,
          "default": "'EUR'"
        },
        "onboarding_completed": {
          "name": "onboarding_completed",
          "type": "boolean",
          "primaryKey": false,
          "notNull": false,
          "default": false
        },
        "created_at": {
          "name": "created_at",
          "type": "timestamp with time zone",
          "primaryKey": false,
          "notNull": true,
          "default": "now()"
        },
        "updated_at": {
          "name": "updated_at",
          "type": "timestamp with time zone",
          "primaryKey": false,
          "notNull": true,
          "default": "now()"
        }
      },
      "indexes": {},
      "foreignKeys": {},
      "compositePrimaryKeys": {},
      "uniqueConstraints": {}
    },
    "public.accounts": {
      "name": "accounts",
      "schema": "",
      "columns": {
        "id": {
          "name": "id",
          "type": "uuid",
          "primaryKey": true,
          "notNull": true,
          "default": "gen_random_uuid()"
        },
        "user_id": {
          "name": "user_id",
          "type": "uuid",
          "primaryKey": false,
          "notNull": true
        },
        "name": {
          "name": "name",
          "type": "text",
          "primaryKey": false,
          "notNull": true
        },
        "institution": {
          "name": "institution",
          "type": "text",
          "primaryKey": false,
          "notNull": false
        },
        "account_type": {
          "name": "account_type",
          "type": "account_type",
          "typeSchema": "public",
          "primaryKey": false,
          "notNull": true
        },
        "currency": {
          "name": "currency",
          "type": "text",
          "primaryKey": false,
          "notNull": true,
          "default": "'EUR'"
        },
        "is_accessible_savings": {
          "name": "is_accessible_savings",
          "type": "boolean",
          "primaryKey": false,
          "notNull": false,
          "default": false
        },
        "is_active": {
          "name": "is_active",
          "type": "boolean",
          "primaryKey": false,
          "notNull": false,
          "default": true
        },
        "display_order": {
          "name": "display_order",
          "type": "integer",
          "primaryKey": false,
          "notNull": false
        },
        "last_import_at": {
          "name": "last_import_at",
          "type": "timestamp with time zone",
          "primaryKey": false,
          "notNull": false
        },
        "created_at": {
          "name": "created_at",
          "type": "timestamp with time zone",
          "primaryKey": false,
          "notNull": true,
          "default": "now()"
        },
        "updated_at": {
          "name": "updated_at",
          "type": "timestamp with time zone",
          "primaryKey": false,
          "notNull": true,
          "default": "now()"
        }
      },
      "indexes": {},
      "foreignKeys": {
        "accounts_user_id_users_id_fk": {
          "name": "accounts_user_id_users_id_fk",
          "tableFrom": "accounts",
          "tableTo": "users",
          "columnsFrom": [
            "user_id"
          ],
          "columnsTo": [
            "id"
          ],
          "onDelete": "cascade",
          "onUpdate": "no action"
        }
      },
      "compositePrimaryKeys": {},
      "uniqueConstraints": {}
    },
    "public.categories": {
      "name": "categories",
      "schema": "",
      "columns": {
        "id": {
          "name": "id",
          "type": "uuid",
          "primaryKey": true,
          "notNull": true,
          "default": "gen_random_uuid()"
        },
        "user_id": {
          "name": "user_id",
          "type": "uuid",
          "primaryKey": false,
          "notNull": false
        },
        "name": {
          "name": "name",
          "type": "text",
          "primaryKey": false,
          "notNull": true
        },
        "icon": {
          "name": "icon",
          "type": "text",
          "primaryKey": false,
          "notNull": false
        },
        "color": {
          "name": "color",
          "type": "text",
          "primaryKey": false,
          "notNull": false
        },
        "parent_id": {
          "name": "parent_id",
          "type": "uuid",
          "primaryKey": false,
          "notNull": false
        },
        "is_system": {
          "name": "is_system",
          "type": "boolean",
          "primaryKey": false,
          "notNull": false,
          "default": false
        },
        "display_order": {
          "name": "display_order",
          "type": "integer",
          "primaryKey": false,
          "notNull": false
        },
        "created_at": {
          "name": "created_at",
          "type": "timestamp with time zone",
          "primaryKey": false,
          "notNull": true,
          "default": "now()"
        },
        "updated_at": {
          "name": "updated_at",
          "type": "timestamp with time zone",
          "primaryKey": false,
          "notNull": true,
          "default": "now()"
        }
      },
      "indexes": {},
      "foreignKeys": {
        "categories_user_id_users_id_fk": {
          "name": "categories_user_id_users_id_fk",
          "tableFrom": "categories",
          "tableTo": "users",
          "columnsFrom": [
            "user_id"
          ],
          "columnsTo": [
            "id"
          ],
          "onDelete": "cascade",
          "onUpdate": "no action"
        }
      },
      "compositePrimaryKeys": {},
      "uniqueConstraints": {}
    },
    "public.import_batches": {
      "name": "import_batches",
      "schema": "",
      "columns": {
        "id": {
          "name": "id",
          "type": "uuid",
          "primaryKey": true,
          "notNull": true,
          "default": "gen_random_uuid()"
        },
        "user_id": {
          "name": "user_id",
          "type": "uuid",
          "primaryKey": false,
          "notNull": true
        },
        "account_id": {
          "name": "account_id",
          "type": "uuid",
          "primaryKey": false,
          "notNull": true
        },
        "source": {
          "name": "source",
          "type": "text",
          "primaryKey": false,
          "notNull": true
        },
        "original_filename": {
          "name": "original_filename",
          "type": "text",
          "primaryKey": false,
          "notNull": false
        },
        "file_hash": {
          "name": "file_hash",
          "type": "text",
          "primaryKey": false,
          "notNull": true
        },
        "row_count": {
          "name": "row_count",
          "type": "integer",
          "primaryKey": false,
          "notNull": false
        },
        "imported_count": {
          "name": "imported_count",
          "type": "integer",
          "primaryKey": false,
          "notNull": false
        },
        "duplicate_count": {
          "name": "duplicate_count",
          "type": "integer",
          "primaryKey": false,
          "notNull": false
        },
        "review_status": {
          "name": "review_status",
          "type": "text",
          "primaryKey": false,
          "notNull": false
        },
        "import_started_at": {
          "name": "import_started_at",
          "type": "timestamp with time zone",
          "primaryKey": false,
          "notNull": false
        },
        "import_completed_at": {
          "name": "import_completed_at",
          "type": "timestamp with time zone",
          "primaryKey": false,
          "notNull": false
        },
        "created_at": {
          "name": "created_at",
          "type": "timestamp with time zone",
          "primaryKey": false,
          "notNull": true,
          "default": "now()"
        },
        "updated_at": {
          "name": "updated_at",
          "type": "timestamp with time zone",
          "primaryKey": false,
          "notNull": true,
          "default": "now()"
        }
      },
      "indexes": {},
      "foreignKeys": {
        "import_batches_user_id_users_id_fk": {
          "name": "import_batches_user_id_users_id_fk",
          "tableFrom": "import_batches",
          "tableTo": "users",
          "columnsFrom": [
            "user_id"
          ],
          "columnsTo": [
            "id"
          ],
          "onDelete": "cascade",
          "onUpdate": "no action"
        },
        "import_batches_account_id_accounts_id_fk": {
          "name": "import_batches_account_id_accounts_id_fk",
          "tableFrom": "import_batches",
          "tableTo": "accounts",
          "columnsFrom": [
            "account_id"
          ],
          "columnsTo": [
            "id"
          ],
          "onDelete": "cascade",
          "onUpdate": "no action"
        }
      },
      "compositePrimaryKeys": {},
      "uniqueConstraints": {
        "import_batches_user_id_file_hash_unique": {
          "name": "import_batches_user_id_file_hash_unique",
          "nullsNotDistinct": false,
          "columns": [
            "user_id",
            "file_hash"
          ]
        }
      }
    },
    "public.transactions": {
      "name": "transactions",
      "schema": "",
      "columns": {
        "id": {
          "name": "id",
          "type": "uuid",
          "primaryKey": true,
          "notNull": true,
          "default": "gen_random_uuid()"
        },
        "user_id": {
          "name": "user_id",
          "type": "uuid",
          "primaryKey": false,
          "notNull": true
        },
        "account_id": {
          "name": "account_id",
          "type": "uuid",
          "primaryKey": false,
          "notNull": true
        },
        "source": {
          "name": "source",
          "type": "text",
          "primaryKey": false,
          "notNull": true
        },
        "external_id": {
          "name": "external_id",
          "type": "text",
          "primaryKey": false,
          "notNull": false
        },
        "occurred_at": {
          "name": "occurred_at",
          "type": "timestamp with time zone",
          "primaryKey": false,
          "notNull": true
        },
        "settled_at": {
          "name": "settled_at",
          "type": "timestamp with time zone",
          "primaryKey": false,
          "notNull": false
        },
        "amount": {
          "name": "amount",
          "type": "integer",
          "primaryKey": false,
          "notNull": true
        },
        "currency": {
          "name": "currency",
          "type": "text",
          "primaryKey": false,
          "notNull": true,
          "default": "'EUR'"
        },
        "raw_description": {
          "name": "raw_description",
          "type": "text",
          "primaryKey": false,
          "notNull": true
        },
        "import_batch_id": {
          "name": "import_batch_id",
          "type": "uuid",
          "primaryKey": false,
          "notNull": false
        },
        "normalized_description": {
          "name": "normalized_description",
          "type": "text",
          "primaryKey": false,
          "notNull": false
        },
        "merchant_name": {
          "name": "merchant_name",
          "type": "text",
          "primaryKey": false,
          "notNull": false
        },
        "intent": {
          "name": "intent",
          "type": "intent",
          "typeSchema": "public",
          "primaryKey": false,
          "notNull": true,
          "default": "'unclassified'"
        },
        "category_id": {
          "name": "category_id",
          "type": "uuid",
          "primaryKey": false,
          "notNull": false
        },
        "review_status": {
          "name": "review_status",
          "type": "review_status",
          "typeSchema": "public",
          "primaryKey": false,
          "notNull": true,
          "default": "'pending'"
        },
        "notes": {
          "name": "notes",
          "type": "text",
          "primaryKey": false,
          "notNull": false
        },
        "created_at": {
          "name": "created_at",
          "type": "timestamp with time zone",
          "primaryKey": false,
          "notNull": true,
          "default": "now()"
        },
        "updated_at": {
          "name": "updated_at",
          "type": "timestamp with time zone",
          "primaryKey": false,
          "notNull": true,
          "default": "now()"
        }
      },
      "indexes": {
        "idx_transactions_user_occurred_at": {
          "name": "idx_transactions_user_occurred_at",
          "columns": [
            "user_id",
            "occurred_at"
          ],
          "isUnique": false
        },
        "idx_transactions_user_intent": {
          "name": "idx_transactions_user_intent",
          "columns": [
            "user_id",
            "intent"
          ],
          "isUnique": false
        },
        "idx_transactions_user_review_status": {
          "name": "idx_transactions_user_review_status",
          "columns": [
            "user_id",
            "review_status"
          ],
          "isUnique": false
        }
      },
      "foreignKeys": {
        "transactions_user_id_users_id_fk": {
          "name": "transactions_user_id_users_id_fk",
          "tableFrom": "transactions",
          "tableTo": "users",
          "columnsFrom": [
            "user_id"
          ],
          "columnsTo": [
            "id"
          ],
          "onDelete": "cascade",
          "onUpdate": "no action"
        },
        "transactions_account_id_accounts_id_fk": {
          "name": "transactions_account_id_accounts_id_fk",
          "tableFrom": "transactions",
          "tableTo": "accounts",
          "columnsFrom": [
            "account_id"
          ],
          "columnsTo": [
            "id"
          ],
          "onDelete": "cascade",
          "onUpdate": "no action"
        },
        "transactions_import_batch_id_import_batches_id_fk": {
          "name": "transactions_import_batch_id_import_batches_id_fk",
          "tableFrom": "transactions",
          "tableTo": "import_batches",
          "columnsFrom": [
            "import_batch_id"
          ],
          "columnsTo": [
            "id"
          ],
          "onDelete": "no action",
          "onUpdate": "no action"
        },
        "transactions_category_id_categories_id_fk": {
          "name": "transactions_category_id_categories_id_fk",
          "tableFrom": "transactions",
          "tableTo": "categories",
          "columnsFrom": [
            "category_id"
          ],
          "columnsTo": [
            "id"
          ],
          "onDelete": "no action",
          "onUpdate": "no action"
        }
      },
      "compositePrimaryKeys": {},
      "uniqueConstraints": {
        "transactions_account_id_external_id_unique": {
          "name": "transactions_account_id_external_id_unique",
          "nullsNotDistinct": false,
          "columns": [
            "account_id",
            "external_id"
          ]
        }
      }
    },
    "public.import_rows": {
      "name": "import_rows",
      "schema": "",
      "columns": {
        "id": {
          "name": "id",
          "type": "uuid",
          "primaryKey": true,
          "notNull": true,
          "default": "gen_random_uuid()"
        },
        "import_batch_id": {
          "name": "import_batch_id",
          "type": "uuid",
          "primaryKey": false,
          "notNull": true
        },
        "user_id": {
          "name": "user_id",
          "type": "uuid",
          "primaryKey": false,
          "notNull": true
        },
        "row_index": {
          "name": "row_index",
          "type": "integer",
          "primaryKey": false,
          "notNull": true
        },
        "raw_data": {
          "name": "raw_data",
          "type": "jsonb",
          "primaryKey": false,
          "notNull": true
        },
        "parse_status": {
          "name": "parse_status",
          "type": "text",
          "primaryKey": false,
          "notNull": true
        },
        "parse_error": {
          "name": "parse_error",
          "type": "text",
          "primaryKey": false,
          "notNull": false
        },
        "transaction_id": {
          "name": "transaction_id",
          "type": "uuid",
          "primaryKey": false,
          "notNull": false
        },
        "created_at": {
          "name": "created_at",
          "type": "timestamp with time zone",
          "primaryKey": false,
          "notNull": true,
          "default": "now()"
        }
      },
      "indexes": {},
      "foreignKeys": {
        "import_rows_import_batch_id_import_batches_id_fk": {
          "name": "import_rows_import_batch_id_import_batches_id_fk",
          "tableFrom": "import_rows",
          "tableTo": "import_batches",
          "columnsFrom": [
            "import_batch_id"
          ],
          "columnsTo": [
            "id"
          ],
          "onDelete": "cascade",
          "onUpdate": "no action"
        },
        "import_rows_user_id_users_id_fk": {
          "name": "import_rows_user_id_users_id_fk",
          "tableFrom": "import_rows",
          "tableTo": "users",
          "columnsFrom": [
            "user_id"
          ],
          "columnsTo": [
            "id"
          ],
          "onDelete": "cascade",
          "onUpdate": "no action"
        },
        "import_rows_transaction_id_transactions_id_fk": {
          "name": "import_rows_transaction_id_transactions_id_fk",
          "tableFrom": "import_rows",
          "tableTo": "transactions",
          "columnsFrom": [
            "transaction_id"
          ],
          "columnsTo": [
            "id"
          ],
          "onDelete": "no action",
          "onUpdate": "no action"
        }
      },
      "compositePrimaryKeys": {},
      "uniqueConstraints": {}
    },
    "public.transfer_links": {
      "name": "transfer_links",
      "schema": "",
      "columns": {
        "id": {
          "name": "id",
          "type": "uuid",
          "primaryKey": true,
          "notNull": true,
          "default": "gen_random_uuid()"
        },
        "user_id": {
          "name": "user_id",
          "type": "uuid",
          "primaryKey": false,
          "notNull": true
        },
        "from_transaction_id": {
          "name": "from_transaction_id",
          "type": "uuid",
          "primaryKey": false,
          "notNull": true
        },
        "to_transaction_id": {
          "name": "to_transaction_id",
          "type": "uuid",
          "primaryKey": false,
          "notNull": true
        },
        "confirmed_by": {
          "name": "confirmed_by",
          "type": "text",
          "primaryKey": false,
          "notNull": false
        },
        "created_at": {
          "name": "created_at",
          "type": "timestamp with time zone",
          "primaryKey": false,
          "notNull": true,
          "default": "now()"
        }
      },
      "indexes": {},
      "foreignKeys": {
        "transfer_links_user_id_users_id_fk": {
          "name": "transfer_links_user_id_users_id_fk",
          "tableFrom": "transfer_links",
          "tableTo": "users",
          "columnsFrom": [
            "user_id"
          ],
          "columnsTo": [
            "id"
          ],
          "onDelete": "cascade",
          "onUpdate": "no action"
        },
        "transfer_links_from_transaction_id_transactions_id_fk": {
          "name": "transfer_links_from_transaction_id_transactions_id_fk",
          "tableFrom": "transfer_links",
          "tableTo": "transactions",
          "columnsFrom": [
            "from_transaction_id"
          ],
          "columnsTo": [
            "id"
          ],
          "onDelete": "cascade",
          "onUpdate": "no action"
        },
        "transfer_links_to_transaction_id_transactions_id_fk": {
          "name": "transfer_links_to_transaction_id_transactions_id_fk",
          "tableFrom": "transfer_links",
          "tableTo": "transactions",
          "columnsFrom": [
            "to_transaction_id"
          ],
          "columnsTo": [
            "id"
          ],
          "onDelete": "cascade",
          "onUpdate": "no action"
        }
      },
      "compositePrimaryKeys": {},
      "uniqueConstraints": {
        "transfer_links_from_transaction_id_unique": {
          "name": "transfer_links_from_transaction_id_unique",
          "nullsNotDistinct": false,
          "columns": [
            "from_transaction_id"
          ]
        },
        "transfer_links_to_transaction_id_unique": {
          "name": "transfer_links_to_transaction_id_unique",
          "nullsNotDistinct": false,
          "columns": [
            "to_transaction_id"
          ]
        }
      }
    },
    "public.reimbursement_links": {
      "name": "reimbursement_links",
      "schema": "",
      "columns": {
        "id": {
          "name": "id",
          "type": "uuid",
          "primaryKey": true,
          "notNull": true,
          "default": "gen_random_uuid()"
        },
        "user_id": {
          "name": "user_id",
          "type": "uuid",
          "primaryKey": false,
          "notNull": true
        },
        "out_transaction_id": {
          "name": "out_transaction_id",
          "type": "uuid",
          "primaryKey": false,
          "notNull": true
        },
        "in_transaction_id": {
          "name": "in_transaction_id",
          "type": "uuid",
          "primaryKey": false,
          "notNull": false
        },
        "expected_amount": {
          "name": "expected_amount",
          "type": "integer",
          "primaryKey": false,
          "notNull": false
        },
        "currency": {
          "name": "currency",
          "type": "text",
          "primaryKey": false,
          "notNull": true,
          "default": "'EUR'"
        },
        "status": {
          "name": "status",
          "type": "text",
          "primaryKey": false,
          "notNull": true
        },
        "notes": {
          "name": "notes",
          "type": "text",
          "primaryKey": false,
          "notNull": false
        },
        "created_at": {
          "name": "created_at",
          "type": "timestamp with time zone",
          "primaryKey": false,
          "notNull": true,
          "default": "now()"
        },
        "updated_at": {
          "name": "updated_at",
          "type": "timestamp with time zone",
          "primaryKey": false,
          "notNull": true,
          "default": "now()"
        }
      },
      "indexes": {},
      "foreignKeys": {
        "reimbursement_links_user_id_users_id_fk": {
          "name": "reimbursement_links_user_id_users_id_fk",
          "tableFrom": "reimbursement_links",
          "tableTo": "users",
          "columnsFrom": [
            "user_id"
          ],
          "columnsTo": [
            "id"
          ],
          "onDelete": "cascade",
          "onUpdate": "no action"
        },
        "reimbursement_links_out_transaction_id_transactions_id_fk": {
          "name": "reimbursement_links_out_transaction_id_transactions_id_fk",
          "tableFrom": "reimbursement_links",
          "tableTo": "transactions",
          "columnsFrom": [
            "out_transaction_id"
          ],
          "columnsTo": [
            "id"
          ],
          "onDelete": "cascade",
          "onUpdate": "no action"
        },
        "reimbursement_links_in_transaction_id_transactions_id_fk": {
          "name": "reimbursement_links_in_transaction_id_transactions_id_fk",
          "tableFrom": "reimbursement_links",
          "tableTo": "transactions",
          "columnsFrom": [
            "in_transaction_id"
          ],
          "columnsTo": [
            "id"
          ],
          "onDelete": "no action",
          "onUpdate": "no action"
        }
      },
      "compositePrimaryKeys": {},
      "uniqueConstraints": {}
    },
    "public.rules": {
      "name": "rules",
      "schema": "",
      "columns": {
        "id": {
          "name": "id",
          "type": "uuid",
          "primaryKey": true,
          "notNull": true,
          "default": "gen_random_uuid()"
        },
        "user_id": {
          "name": "user_id",
          "type": "uuid",
          "primaryKey": false,
          "notNull": true
        },
        "name": {
          "name": "name",
          "type": "text",
          "primaryKey": false,
          "notNull": false
        },
        "match_field": {
          "name": "match_field",
          "type": "text",
          "primaryKey": false,
          "notNull": true
        },
        "match_operator": {
          "name": "match_operator",
          "type": "text",
          "primaryKey": false,
          "notNull": true
        },
        "match_value": {
          "name": "match_value",
          "type": "text",
          "primaryKey": false,
          "notNull": true
        },
        "set_intent": {
          "name": "set_intent",
          "type": "text",
          "primaryKey": false,
          "notNull": false
        },
        "set_category_id": {
          "name": "set_category_id",
          "type": "uuid",
          "primaryKey": false,
          "notNull": false
        },
        "set_merchant_name": {
          "name": "set_merchant_name",
          "type": "text",
          "primaryKey": false,
          "notNull": false
        },
        "priority": {
          "name": "priority",
          "type": "integer",
          "primaryKey": false,
          "notNull": false
        },
        "is_active": {
          "name": "is_active",
          "type": "boolean",
          "primaryKey": false,
          "notNull": false,
          "default": true
        },
        "applied_count": {
          "name": "applied_count",
          "type": "integer",
          "primaryKey": false,
          "notNull": false,
          "default": 0
        },
        "created_at": {
          "name": "created_at",
          "type": "timestamp with time zone",
          "primaryKey": false,
          "notNull": true,
          "default": "now()"
        },
        "updated_at": {
          "name": "updated_at",
          "type": "timestamp with time zone",
          "primaryKey": false,
          "notNull": true,
          "default": "now()"
        }
      },
      "indexes": {},
      "foreignKeys": {
        "rules_user_id_users_id_fk": {
          "name": "rules_user_id_users_id_fk",
          "tableFrom": "rules",
          "tableTo": "users",
          "columnsFrom": [
            "user_id"
          ],
          "columnsTo": [
            "id"
          ],
          "onDelete": "cascade",
          "onUpdate": "no action"
        },
        "rules_set_category_id_categories_id_fk": {
          "name": "rules_set_category_id_categories_id_fk",
          "tableFrom": "rules",
          "tableTo": "categories",
          "columnsFrom": [
            "set_category_id"
          ],
          "columnsTo": [
            "id"
          ],
          "onDelete": "no action",
          "onUpdate": "no action"
        }
      },
      "compositePrimaryKeys": {},
      "uniqueConstraints": {}
    },
    "public.recurring_series": {
      "name": "recurring_series",
      "schema": "",
      "columns": {
        "id": {
          "name": "id",
          "type": "uuid",
          "primaryKey": true,
          "notNull": true,
          "default": "gen_random_uuid()"
        },
        "user_id": {
          "name": "user_id",
          "type": "uuid",
          "primaryKey": false,
          "notNull": true
        },
        "account_id": {
          "name": "account_id",
          "type": "uuid",
          "primaryKey": false,
          "notNull": false
        },
        "name": {
          "name": "name",
          "type": "text",
          "primaryKey": false,
          "notNull": true
        },
        "amount": {
          "name": "amount",
          "type": "integer",
          "primaryKey": false,
          "notNull": true
        },
        "currency": {
          "name": "currency",
          "type": "text",
          "primaryKey": false,
          "notNull": true,
          "default": "'EUR'"
        },
        "intent": {
          "name": "intent",
          "type": "text",
          "primaryKey": false,
          "notNull": true
        },
        "category_id": {
          "name": "category_id",
          "type": "uuid",
          "primaryKey": false,
          "notNull": false
        },
        "frequency": {
          "name": "frequency",
          "type": "text",
          "primaryKey": false,
          "notNull": true
        },
        "day_of_month": {
          "name": "day_of_month",
          "type": "integer",
          "primaryKey": false,
          "notNull": false
        },
        "month_of_year": {
          "name": "month_of_year",
          "type": "integer",
          "primaryKey": false,
          "notNull": false
        },
        "next_expected_at": {
          "name": "next_expected_at",
          "type": "timestamp with time zone",
          "primaryKey": false,
          "notNull": false
        },
        "last_matched_at": {
          "name": "last_matched_at",
          "type": "timestamp with time zone",
          "primaryKey": false,
          "notNull": false
        },
        "is_active": {
          "name": "is_active",
          "type": "boolean",
          "primaryKey": false,
          "notNull": false,
          "default": true
        },
        "created_at": {
          "name": "created_at",
          "type": "timestamp with time zone",
          "primaryKey": false,
          "notNull": true,
          "default": "now()"
        },
        "updated_at": {
          "name": "updated_at",
          "type": "timestamp with time zone",
          "primaryKey": false,
          "notNull": true,
          "default": "now()"
        }
      },
      "indexes": {},
      "foreignKeys": {
        "recurring_series_user_id_users_id_fk": {
          "name": "recurring_series_user_id_users_id_fk",
          "tableFrom": "recurring_series",
          "tableTo": "users",
          "columnsFrom": [
            "user_id"
          ],
          "columnsTo": [
            "id"
          ],
          "onDelete": "cascade",
          "onUpdate": "no action"
        },
        "recurring_series_account_id_accounts_id_fk": {
          "name": "recurring_series_account_id_accounts_id_fk",
          "tableFrom": "recurring_series",
          "tableTo": "accounts",
          "columnsFrom": [
            "account_id"
          ],
          "columnsTo": [
            "id"
          ],
          "onDelete": "no action",
          "onUpdate": "no action"
        },
        "recurring_series_category_id_categories_id_fk": {
          "name": "recurring_series_category_id_categories_id_fk",
          "tableFrom": "recurring_series",
          "tableTo": "categories",
          "columnsFrom": [
            "category_id"
          ],
          "columnsTo": [
            "id"
          ],
          "onDelete": "no action",
          "onUpdate": "no action"
        }
      },
      "compositePrimaryKeys": {},
      "uniqueConstraints": {}
    },
    "public.budget_periods": {
      "name": "budget_periods",
      "schema": "",
      "columns": {
        "id": {
          "name": "id",
          "type": "uuid",
          "primaryKey": true,
          "notNull": true,
          "default": "gen_random_uuid()"
        },
        "user_id": {
          "name": "user_id",
          "type": "uuid",
          "primaryKey": false,
          "notNull": true
        },
        "year": {
          "name": "year",
          "type": "integer",
          "primaryKey": false,
          "notNull": true
        },
        "month": {
          "name": "month",
          "type": "integer",
          "primaryKey": false,
          "notNull": true
        },
        "expected_income": {
          "name": "expected_income",
          "type": "integer",
          "primaryKey": false,
          "notNull": false
        },
        "planned_investing": {
          "name": "planned_investing",
          "type": "integer",
          "primaryKey": false,
          "notNull": false
        },
        "investing_protected": {
          "name": "investing_protected",
          "type": "boolean",
          "primaryKey": false,
          "notNull": false
        },
        "notes": {
          "name": "notes",
          "type": "text",
          "primaryKey": false,
          "notNull": false
        },
        "created_at": {
          "name": "created_at",
          "type": "timestamp with time zone",
          "primaryKey": false,
          "notNull": true,
          "default": "now()"
        },
        "updated_at": {
          "name": "updated_at",
          "type": "timestamp with time zone",
          "primaryKey": false,
          "notNull": true,
          "default": "now()"
        }
      },
      "indexes": {},
      "foreignKeys": {
        "budget_periods_user_id_users_id_fk": {
          "name": "budget_periods_user_id_users_id_fk",
          "tableFrom": "budget_periods",
          "tableTo": "users",
          "columnsFrom": [
            "user_id"
          ],
          "columnsTo": [
            "id"
          ],
          "onDelete": "cascade",
          "onUpdate": "no action"
        }
      },
      "compositePrimaryKeys": {},
      "uniqueConstraints": {
        "budget_periods_user_id_year_month_unique": {
          "name": "budget_periods_user_id_year_month_unique",
          "nullsNotDistinct": false,
          "columns": [
            "user_id",
            "year",
            "month"
          ]
        }
      }
    },
    "public.sinking_funds": {
      "name": "sinking_funds",
      "schema": "",
      "columns": {
        "id": {
          "name": "id",
          "type": "uuid",
          "primaryKey": true,
          "notNull": true,
          "default": "gen_random_uuid()"
        },
        "user_id": {
          "name": "user_id",
          "type": "uuid",
          "primaryKey": false,
          "notNull": true
        },
        "name": {
          "name": "name",
          "type": "text",
          "primaryKey": false,
          "notNull": true
        },
        "target_amount": {
          "name": "target_amount",
          "type": "integer",
          "primaryKey": false,
          "notNull": true
        },
        "currency": {
          "name": "currency",
          "type": "text",
          "primaryKey": false,
          "notNull": true,
          "default": "'EUR'"
        },
        "monthly_allocation": {
          "name": "monthly_allocation",
          "type": "integer",
          "primaryKey": false,
          "notNull": true
        },
        "current_balance": {
          "name": "current_balance",
          "type": "integer",
          "primaryKey": false,
          "notNull": false
        },
        "target_date": {
          "name": "target_date",
          "type": "date",
          "primaryKey": false,
          "notNull": false
        },
        "is_active": {
          "name": "is_active",
          "type": "boolean",
          "primaryKey": false,
          "notNull": false,
          "default": true
        },
        "created_at": {
          "name": "created_at",
          "type": "timestamp with time zone",
          "primaryKey": false,
          "notNull": true,
          "default": "now()"
        },
        "updated_at": {
          "name": "updated_at",
          "type": "timestamp with time zone",
          "primaryKey": false,
          "notNull": true,
          "default": "now()"
        }
      },
      "indexes": {},
      "foreignKeys": {
        "sinking_funds_user_id_users_id_fk": {
          "name": "sinking_funds_user_id_users_id_fk",
          "tableFrom": "sinking_funds",
          "tableTo": "users",
          "columnsFrom": [
            "user_id"
          ],
          "columnsTo": [
            "id"
          ],
          "onDelete": "cascade",
          "onUpdate": "no action"
        }
      },
      "compositePrimaryKeys": {},
      "uniqueConstraints": {}
    },
    "public.safe_to_spend_snapshots": {
      "name": "safe_to_spend_snapshots",
      "schema": "",
      "columns": {
        "id": {
          "name": "id",
          "type": "uuid",
          "primaryKey": true,
          "notNull": true,
          "default": "gen_random_uuid()"
        },
        "user_id": {
          "name": "user_id",
          "type": "uuid",
          "primaryKey": false,
          "notNull": true
        },
        "computed_at": {
          "name": "computed_at",
          "type": "timestamp with time zone",
          "primaryKey": false,
          "notNull": true
        },
        "value_cents": {
          "name": "value_cents",
          "type": "integer",
          "primaryKey": false,
          "notNull": true
        },
        "spendable_pool_cents": {
          "name": "spendable_pool_cents",
          "type": "integer",
          "primaryKey": false,
          "notNull": true
        },
        "days_until_payday": {
          "name": "days_until_payday",
          "type": "integer",
          "primaryKey": false,
          "notNull": true
        },
        "available_cash_cents": {
          "name": "available_cash_cents",
          "type": "integer",
          "primaryKey": false,
          "notNull": true
        },
        "protected_total_cents": {
          "name": "protected_total_cents",
          "type": "integer",
          "primaryKey": false,
          "notNull": true
        },
        "upcoming_bills_cents": {
          "name": "upcoming_bills_cents",
          "type": "integer",
          "primaryKey": false,
          "notNull": true
        },
        "sinking_fund_cents": {
          "name": "sinking_fund_cents",
          "type": "integer",
          "primaryKey": false,
          "notNull": true
        },
        "min_buffer_cents": {
          "name": "min_buffer_cents",
          "type": "integer",
          "primaryKey": false,
          "notNull": true
        },
        "investing_cents": {
          "name": "investing_cents",
          "type": "integer",
          "primaryKey": false,
          "notNull": true
        },
        "anomaly_reserve_cents": {
          "name": "anomaly_reserve_cents",
          "type": "integer",
          "primaryKey": false,
          "notNull": true
        },
        "investing_protected": {
          "name": "investing_protected",
          "type": "boolean",
          "primaryKey": false,
          "notNull": true
        },
        "assumption_trail": {
          "name": "assumption_trail",
          "type": "jsonb",
          "primaryKey": false,
          "notNull": true
        },
        "warnings": {
          "name": "warnings",
          "type": "jsonb",
          "primaryKey": false,
          "notNull": false
        },
        "created_at": {
          "name": "created_at",
          "type": "timestamp with time zone",
          "primaryKey": false,
          "notNull": true,
          "default": "now()"
        }
      },
      "indexes": {},
      "foreignKeys": {
        "safe_to_spend_snapshots_user_id_users_id_fk": {
          "name": "safe_to_spend_snapshots_user_id_users_id_fk",
          "tableFrom": "safe_to_spend_snapshots",
          "tableTo": "users",
          "columnsFrom": [
            "user_id"
          ],
          "columnsTo": [
            "id"
          ],
          "onDelete": "cascade",
          "onUpdate": "no action"
        }
      },
      "compositePrimaryKeys": {},
      "uniqueConstraints": {}
    },
    "public.audit_logs": {
      "name": "audit_logs",
      "schema": "",
      "columns": {
        "id": {
          "name": "id",
          "type": "uuid",
          "primaryKey": true,
          "notNull": true,
          "default": "gen_random_uuid()"
        },
        "user_id": {
          "name": "user_id",
          "type": "uuid",
          "primaryKey": false,
          "notNull": true
        },
        "table_name": {
          "name": "table_name",
          "type": "text",
          "primaryKey": false,
          "notNull": true
        },
        "record_id": {
          "name": "record_id",
          "type": "uuid",
          "primaryKey": false,
          "notNull": true
        },
        "action": {
          "name": "action",
          "type": "text",
          "primaryKey": false,
          "notNull": true
        },
        "changed_fields": {
          "name": "changed_fields",
          "type": "jsonb",
          "primaryKey": false,
          "notNull": false
        },
        "actor": {
          "name": "actor",
          "type": "text",
          "primaryKey": false,
          "notNull": false
        },
        "created_at": {
          "name": "created_at",
          "type": "timestamp with time zone",
          "primaryKey": false,
          "notNull": true,
          "default": "now()"
        }
      },
      "indexes": {},
      "foreignKeys": {
        "audit_logs_user_id_users_id_fk": {
          "name": "audit_logs_user_id_users_id_fk",
          "tableFrom": "audit_logs",
          "tableTo": "users",
          "columnsFrom": [
            "user_id"
          ],
          "columnsTo": [
            "id"
          ],
          "onDelete": "cascade",
          "onUpdate": "no action"
        }
      },
      "compositePrimaryKeys": {},
      "uniqueConstraints": {}
    },
    "public.beta_signups": {
      "name": "beta_signups",
      "schema": "",
      "columns": {
        "id": {
          "name": "id",
          "type": "uuid",
          "primaryKey": true,
          "notNull": true,
          "default": "gen_random_uuid()"
        },
        "email": {
          "name": "email",
          "type": "text",
          "primaryKey": false,
          "notNull": true
        },
        "primary_bank": {
          "name": "primary_bank",
          "type": "text",
          "primaryKey": false,
          "notNull": true
        },
        "broker": {
          "name": "broker",
          "type": "text",
          "primaryKey": false,
          "notNull": true
        },
        "reason": {
          "name": "reason",
          "type": "text",
          "primaryKey": false,
          "notNull": true
        },
        "ticket_id": {
          "name": "ticket_id",
          "type": "text",
          "primaryKey": false,
          "notNull": true
        },
        "status": {
          "name": "status",
          "type": "text",
          "primaryKey": false,
          "notNull": true,
          "default": "'pending'"
        },
        "source": {
          "name": "source",
          "type": "text",
          "primaryKey": false,
          "notNull": true,
          "default": "'beta_page'"
        },
        "created_at": {
          "name": "created_at",
          "type": "timestamp with time zone",
          "primaryKey": false,
          "notNull": true,
          "default": "now()"
        },
        "updated_at": {
          "name": "updated_at",
          "type": "timestamp with time zone",
          "primaryKey": false,
          "notNull": true,
          "default": "now()"
        }
      },
      "indexes": {},
      "foreignKeys": {},
      "compositePrimaryKeys": {},
      "uniqueConstraints": {
        "beta_signups_email_unique": {
          "name": "beta_signups_email_unique",
          "nullsNotDistinct": false,
          "columns": [
            "email"
          ]
        },
        "beta_signups_ticket_id_unique": {
          "name": "beta_signups_ticket_id_unique",
          "nullsNotDistinct": false,
          "columns": [
            "ticket_id"
          ]
        }
      }
    }
  },
  "enums": {
    "public.account_type": {
      "name": "account_type",
      "schema": "public",
      "values": [
        "checking",
        "savings",
        "credit_card",
        "brokerage",
        "pension",
        "cash",
        "manual_external"
      ]
    },
    "public.intent": {
      "name": "intent",
      "schema": "public",
      "values": [
        "living_expense",
        "recurring_bill",
        "income_salary",
        "income_dividend",
        "income_refund",
        "income_other",
        "transfer",
        "reimbursement_out",
        "reimbursement_in",
        "investment_contribution",
        "investment_buy",
        "investment_sell",
        "fee",
        "tax",
        "adjustment",
        "unclassified"
      ]
    },
    "public.review_status": {
      "name": "review_status",
      "schema": "public",
      "values": [
        "pending",
        "reviewed",
        "needs_attention",
        "auto_approved"
      ]
    }
  },
  "schemas": {},
  "_meta": {
    "columns": {},
    "schemas": {},
    "tables": {}
  }
}